README.md
setup.py
chryso/__init__.py
chryso/connection.py
chryso/constants.py
chryso/errors.py
chryso/fixtures.py
chryso/queryadapter.py
chryso/resource.py
chryso/schema.py
chryso/version.py
chryso.egg-info/PKG-INFO
chryso.egg-info/SOURCES.txt
chryso.egg-info/dependency_links.txt
chryso.egg-info/entry_points.txt
chryso.egg-info/requires.txt
chryso.egg-info/top_level.txt