Metadata-Version: 1.0
Name: chryso
Version: 2.1
Summary: A library for working with Postgres and SQLAlchemy
Home-page: https://bitbucket.com/Authentise/chryso
Author: Authentise, Inc.
Author-email: engineering@authentise.com
License: UNKNOWN
Platform: UNKNOWN
